redis_chatgpt/__init__.py
redis_chatgpt/manager/__init__.py
redis_chatgpt/manager/db_manager.py
redis_chatgpt-0.1.2.dist-info/LICENSE
redis_chatgpt-0.1.2.dist-info/METADATA
redis_chatgpt-0.1.2.dist-info/WHEEL
redis_chatgpt-0.1.2.dist-info/top_level.txt
redis_chatgpt-0.1.2.dist-info/RECORD
