Metadata-Version: 2.1
Name: redis-chatgpt
Version: 0.1.2
Summary: A user-friendly package designed to save chat history conversation and truncate conversation if user exceeds max token when using OpenAI chat completion.
Author: Elmira Ghorbani
Project-URL: Github, https://github.com/ElmiraGhorbani/redis-chatgpt
License-File: LICENSE
Requires-Dist: redis (>=4.6.0)
